contextful/__init__.py
contextful/context_logger.py
contextful/log_context.py
contextful-0.0.1.dist-info/LICENSE
contextful-0.0.1.dist-info/METADATA
contextful-0.0.1.dist-info/WHEEL
contextful-0.0.1.dist-info/RECORD
